sslcheck/__init__.py
sslcheck-1.0.5.dist-info/LICENSE
sslcheck-1.0.5.dist-info/METADATA
sslcheck-1.0.5.dist-info/WHEEL
sslcheck-1.0.5.dist-info/entry_points.txt
sslcheck-1.0.5.dist-info/top_level.txt
sslcheck-1.0.5.dist-info/RECORD
