Metadata-Version: 2.1
Name: sslcheck
Version: 1.0.5
Summary: A simple command line SSL validator
Home-page: http://gitlab.com/radek-sprta/sslcheck
Author: Radek Sprta
Author-email: mail@radeksprta.eu
License: MIT License
Download-URL: https://gitlab.com/radek-sprta/sslcheck/repository/archive.tar.gz?ref=master
Keywords: sslcheck
Platform: UNKNOWN
Classifier: Development Status :: 3 - Alpha
Classifier: Operating System :: POSIX :: Linux
Classifier: Natural Language :: English
Classifier: Environment :: Console
Classifier: Intended Audience :: End Users/Desktop
Classifier: Programming Language :: Python :: 3
Classifier: Programming Language :: Python :: 3.5
Classifier: Programming Language :: Python :: 3.6
Classifier: Programming Language :: Python :: 3.7
Classifier: Programming Language :: Python :: 3.8
Classifier: Programming Language :: Python :: 3.9
Requires-Python: >=3.5
Requires-Dist: certifi
Requires-Dist: pyopenssl
